sourcery_analytics/__init__.py
sourcery_analytics/__main__.py
sourcery_analytics/analysis.py
sourcery_analytics/cli/__init__.py
sourcery_analytics/cli/choices.py
sourcery_analytics/cli/data.py
sourcery_analytics/cli/partials.py
sourcery_analytics/conditions.py
sourcery_analytics/extractors.py
sourcery_analytics/logging.py
sourcery_analytics/main.py
sourcery_analytics/metrics/__init__.py
sourcery_analytics/metrics/aggregations.py
sourcery_analytics/metrics/cognitive_complexity.py
sourcery_analytics/metrics/compounders.py
sourcery_analytics/metrics/cyclomatic_complexity.py
sourcery_analytics/metrics/method_length.py
sourcery_analytics/metrics/types.py
sourcery_analytics/metrics/utils.py
sourcery_analytics/metrics/working_memory.py
sourcery_analytics/settings.py
sourcery_analytics/utils.py
sourcery_analytics/visitors.py
sourcery_analytics-1.2.1.dist-info/entry_points.txt
sourcery_analytics-1.2.1.dist-info/WHEEL
sourcery_analytics-1.2.1.dist-info/METADATA
sourcery_analytics-1.2.1.dist-info/RECORD
