Metadata-Version: 2.1
Name: sourcery-analytics
Version: 1.2.1
Summary: sourcery-analytics is a library and command-line interface (CLI) for analyzing the code quality of Python packages, modules, or source code.
Home-page: https://github.com/sourcery-ai/sourcery-analytics
Keywords: cli,code-quality,python
Author: Ben Martineau
Author-email: ben@sourcery.ai
Requires-Python: >=3.9,<4.0
Classifier: Intended Audience :: Developers
Classifier: Programming Language :: Python :: 3
Classifier: Programming Language :: Python :: 3.9
Classifier: Programming Language :: Python :: 3.10
Classifier: Programming Language :: Python :: 3.9
Requires-Dist: astroid (==2.12.10)
Requires-Dist: more-itertools (==8.14.0)
Requires-Dist: pydantic (==1.10.2)
Requires-Dist: rich (==12.5.1)
Requires-Dist: tomli (==2.0.1)
Requires-Dist: typer (==0.6.1)
Project-URL: Documentation, https://sourcery-analytics.sourcery.ai/
